drf_auto_filters/__init__.py
drf_auto_filters/apps.py
drf_auto_filters/filters.py
drf_auto_filters/schema.py
drf_auto_filters-0.1.0.dist-info/LICENSE
drf_auto_filters-0.1.0.dist-info/METADATA
drf_auto_filters-0.1.0.dist-info/WHEEL
drf_auto_filters-0.1.0.dist-info/top_level.txt
drf_auto_filters-0.1.0.dist-info/RECORD
