Metadata-Version: 2.1
Name: drf-auto-filters
Version: 0.1.0
Summary: Automatic filter generation for Django Rest Framework based on model field types
Author: Victoire HABAMUNGU
Author-email: htvictoire@gmail.com
License: MIT
Project-URL: Documentation, https://github.com/htvictoire/drf-auto-filters
Project-URL: Source, https://github.com/htvictoire/drf-auto-filters
Project-URL: Tracker, https://github.com/htvictoire/drf-auto-filters/issues
Classifier: Development Status :: 4 - Beta
Classifier: Environment :: Web Environment
Classifier: Framework :: Django
Classifier: Framework :: Django :: 3.2
Classifier: Framework :: Django :: 4.0
Classifier: Framework :: Django :: 4.1
Classifier: Framework :: Django :: 4.2
Classifier: Intended Audience :: Developers
Classifier: License :: OSI Approved :: MIT License
Classifier: Operating System :: OS Independent
Classifier: Programming Language :: Python
Classifier: Programming Language :: Python :: 3
Classifier: Programming Language :: Python :: 3.8
Classifier: Programming Language :: Python :: 3.9
Classifier: Programming Language :: Python :: 3.10
Classifier: Programming Language :: Python :: 3.11
Classifier: Topic :: Internet :: WWW/HTTP
Requires-Python: >=3.8
License-File: LICENSE
Requires-Dist: Django>=3.2
Requires-Dist: djangorestframework>=3.12.0
Requires-Dist: django-filter>=22.1
Requires-Dist: drf-yasg>=1.20.0
